tflite_clib_builder/__init__.py
tflite_clib_builder/__main__.py
tflite_clib_builder/builder_factory.py
tflite_clib_builder-1.0.0.dist-info/LICENSE
tflite_clib_builder-1.0.0.dist-info/METADATA
tflite_clib_builder-1.0.0.dist-info/WHEEL
tflite_clib_builder-1.0.0.dist-info/entry_points.txt
tflite_clib_builder-1.0.0.dist-info/top_level.txt
tflite_clib_builder-1.0.0.dist-info/RECORD
