Metadata-Version: 2.1
Name: tflite-clib-builder
Version: 1.0.0
Summary: A Python script to build  Tensorflow-lite's C dynamic/shared library for Windows Unix and Android (No more having to add Tensorflow as a git sub-repo :) )
Author-email: James Calo <jamesafcalo@gmail.com>
License: GNU GENERAL PUBLIC LICENSE
Classifier: Development Status :: 5 - Production/Stable
Classifier: Intended Audience :: Information Technology
Classifier: Intended Audience :: Science/Research
Classifier: License :: OSI Approved :: GNU General Public License v3 (GPLv3)
Classifier: Operating System :: OS Independent
Classifier: Topic :: Scientific/Engineering :: Artificial Intelligence
Requires-Python: >=3.9
License-File: LICENSE
